wikijs/__init__.py
wikijs/asset.py
wikijs/client.py
wikijs/exceptions.py
wikijs/page.py
wikijs/system.py
wikijs/typing.py
wikijs/user.py
wikijs-0.1.dev1.dist-info/LICENSE
wikijs-0.1.dev1.dist-info/METADATA
wikijs-0.1.dev1.dist-info/WHEEL
wikijs-0.1.dev1.dist-info/top_level.txt
wikijs-0.1.dev1.dist-info/RECORD
