Metadata-Version: 2.1
Name: wikijs
Version: 0.1.dev1
Summary: WikiJs API client
Home-page: https://github.com/nuno-andre/python-wikijs#readme
Author: Nuno André
Author-email: mail@nunoand.re
License: BSD-3-Clause
Project-URL: Source, https://github.com/nuno-andre/python-wikijs
Project-URL: Bug Tracker, https://github.com/nuno-andre/python-wikijs/issues
Keywords: wikijs,wiki,graphql
Platform: any
Classifier: Development Status :: 2 - Pre-Alpha
Classifier: Intended Audience :: Developers
Classifier: Intended Audience :: System Administrators
Classifier: License :: OSI Approved :: BSD License
Classifier: Natural Language :: English
Classifier: Operating System :: OS Independent
Classifier: Programming Language :: Python
Classifier: Programming Language :: Python :: 3.7
Classifier: Programming Language :: Python :: 3.8
Classifier: Programming Language :: Python :: 3.9
Classifier: Programming Language :: Python :: 3.10
Classifier: Programming Language :: Python :: 3.11
Classifier: Topic :: Documentation
Classifier: Topic :: Internet :: WWW/HTTP :: Dynamic Content :: Wiki
Classifier: Typing :: Typed
Requires-Python: >=3.7
License-File: LICENSE
Requires-Dist: gql[aiohttp]
Provides-Extra: dev
Requires-Dist: flake8 ; extra == 'dev'
Requires-Dist: mypy ; extra == 'dev'
Requires-Dist: pytest ; extra == 'dev'
Provides-Extra: docs
Requires-Dist: sphinx ; extra == 'docs'
Requires-Dist: sphinx-rtd-theme ; extra == 'docs'
